aiorgwadmin/__init__.py
aiorgwadmin/exceptions.py
aiorgwadmin/py.typed
aiorgwadmin/rgw.py
aiorgwadmin/user.py
aiorgwadmin/utils.py
aiorgwadmin-1.2.0.dist-info/LICENSE
aiorgwadmin-1.2.0.dist-info/METADATA
aiorgwadmin-1.2.0.dist-info/WHEEL
aiorgwadmin-1.2.0.dist-info/top_level.txt
aiorgwadmin-1.2.0.dist-info/RECORD
