Metadata-Version: 2.1
Name: aiorgwadmin
Version: 1.2.0
Summary: Python Rados Gateway Admin API
Home-page: https://github.com/mikle-green/aiorgwadmin
Author: Derek Yarnell <derek@umiacs.umd.edu>, Mikle Green
License: LGPL v2.1
Keywords: ceph,radosgw,admin api,async
Classifier: Development Status :: 5 - Production/Stable
Classifier: Programming Language :: Python :: 3
Classifier: Programming Language :: Python :: 3.10
Requires-Python: >=3.10
License-File: LICENSE
Requires-Dist: aiohttp
Requires-Dist: requests
Requires-Dist: requests-aws
